insh.py
intellishell-0.5.0.dist-info/LICENSE
intellishell-0.5.0.dist-info/METADATA
intellishell-0.5.0.dist-info/WHEEL
intellishell-0.5.0.dist-info/entry_points.txt
intellishell-0.5.0.dist-info/top_level.txt
intellishell-0.5.0.dist-info/RECORD
