Metadata-Version: 2.2
Name: intellishell
Version: 0.5.0
Summary: This is a handler running on top of the Bash shell that implements real-time command history completion from a drop-down list.
Home-page: https://github.com/Lifailon/intellishell
Author: Lifailon
Classifier: Programming Language :: Python :: 3
Classifier: License :: OSI Approved :: MIT License
Classifier: Operating System :: OS Independent
Requires-Python: >=3.6
License-File: LICENSE
Requires-Dist: prompt_toolkit
Dynamic: author
Dynamic: classifier
Dynamic: description
Dynamic: description-content-type
Dynamic: home-page
Dynamic: requires-dist
Dynamic: requires-python
Dynamic: summary
